setup.py
adbutil.egg-info/PKG-INFO
adbutil.egg-info/SOURCES.txt
adbutil.egg-info/dependency_links.txt
adbutil.egg-info/entry_points.txt
adbutil.egg-info/top_level.txt
flash/__init__.py
flash/authorize_usb_keys.py
flash/collect_info.py
flash/collect_info_2_mysql.py
flash/device_setting.py
flash/flash_all.py
flash/flash_magisk_module.py
flash/flash_system.py
flash/flash_twrp.py
flash/frpc_auto.py
flash/frpc_frida.py
flash/frpc_mitm.py
flash/install_app.py
flash/power_off.py
flash/push_certificate_to_system.py
flash/push_certificate_to_user.py
flash/push_something_to_sdcard.py
flash/reboot.py
flash/sqlalchemy_cli.py
flash/su.py