Metadata-Version: 1.0
Name: adbutil
Version: 0.0.6
Summary: android flash update da4
Home-page: https://blog.csdn.net/Jonder_wu?type=blog
Author: jayden
Author-email: 282669595@qq.com
License: UNKNOWN
Platform: UNKNOWN
